falcon_sdk/__init__.py
falcon_sdk/breadcrumbs.py
falcon_sdk/celery.py
falcon_sdk/client.py
falcon_sdk/cron.py
falcon_sdk/django.py
falcon_sdk/fastapi.py
falcon_sdk/flask.py
falcon_sdk/health.py
falcon_sdk/metrics.py
falcon_sdk/types.py
roselabs_falcon-0.2.2.dist-info/METADATA
roselabs_falcon-0.2.2.dist-info/WHEEL
roselabs_falcon-0.2.2.dist-info/RECORD
