Metadata-Version: 2.4
Name: roselabs-falcon
Version: 0.2.2
Summary: Falcon error tracking SDK for Python
Project-URL: Homepage, https://falcon.roselabs.io
Project-URL: Repository, https://github.com/roselabs/falcon-sdk-python
Project-URL: Documentation, https://falcon.roselabs.io/docs
Author-email: RoseLabs <support@roselabs.io>
License-Expression: MIT
Keywords: error-reporting,error-tracking,exception-tracking,falcon,monitoring,roselabs
Classifier: Development Status :: 4 - Beta
Classifier: Intended Audience :: Developers
Classifier: License :: OSI Approved :: MIT License
Classifier: Programming Language :: Python :: 3
Classifier: Programming Language :: Python :: 3.9
Classifier: Programming Language :: Python :: 3.10
Classifier: Programming Language :: Python :: 3.11
Classifier: Programming Language :: Python :: 3.12
Classifier: Topic :: Software Development :: Libraries :: Python Modules
Classifier: Topic :: System :: Monitoring
Requires-Python: >=3.9
Requires-Dist: httpx>=0.25.0
Provides-Extra: all
Requires-Dist: django>=3.2; extra == 'all'
Requires-Dist: psutil>=5.9.0; extra == 'all'
Requires-Dist: starlette>=0.27.0; extra == 'all'
Provides-Extra: dev
Requires-Dist: pytest-asyncio>=0.21.0; extra == 'dev'
Requires-Dist: pytest>=7.0.0; extra == 'dev'
Requires-Dist: ruff>=0.1.0; extra == 'dev'
Requires-Dist: starlette>=0.27.0; extra == 'dev'
Provides-Extra: django
Requires-Dist: django>=3.2; extra == 'django'
Provides-Extra: fastapi
Requires-Dist: starlette>=0.27.0; extra == 'fastapi'
Provides-Extra: metrics
Requires-Dist: psutil>=5.9.0; extra == 'metrics'
